{"Babic\u00eb":394,"Bajram Curri":213,"Bajz\u00eb":211,"Ballsh":313,"Berat":32,"Bilisht":811,"Bulqiz\u00eb":219,"Burrel":217,"Cakran":387,"\u00c7\u00ebrrik":581,"\u00c7orovod\u00eb":312,"Delvin\u00eb":815,"Divjak\u00eb":371,"Durr\u00ebs":52,"Elbasan":545,"Ersek\u00eb":812,"Fier":34,"Fush\u00eb-Kruj\u00eb":563,"Gjirokast\u00ebr":84,"Gramsh":513,"Himar\u00eb":393,"Kavaj\u00eb":554,"Koplik":211,"Kor\u00e7\u00eb":82,"Kruj\u00eb":511,"Krum\u00eb":214,"Ksamil":893,"Ku\u00e7ov\u00eb":311,"Kuk\u00ebs":242,"La\u00e7":53,"Levan":388,"Lezh\u00eb":215,"Libohov\u00eb":881,"Librazhd":514,"Lushnj\u00eb":35,"Maliq":861,"Mamurras":561,"Memaliaj":885,"Mobile":68,"Orikum":391,"Patos":342,"Peqin":512,"P\u00ebrmet":813,"P\u00ebrrenjas":591,"Peshkopi":218,"Pogradec":832,"Poli\u00e7an":368,"Puk\u00eb":212,"Rr\u00ebshen":216,"Rrogozhin\u00eb":577,"Sarand\u00eb":852,"Selenic\u00eb":392,"Shijak":571,"Shkod\u00ebr":22,"Tepelen\u00eb":814,"Tiran\u00eb":4,"Tropoj\u00eb":213,"Ura Vajgurore":361,"Vlor\u00eb":33,"Vodafone":69}